flytekitplugins_data_fsspec-1.16.12-py3.14-nspkg.pth
flytekitplugins/fsspec/__init__.py
flytekitplugins_data_fsspec-1.16.12.dist-info/METADATA
flytekitplugins_data_fsspec-1.16.12.dist-info/WHEEL
flytekitplugins_data_fsspec-1.16.12.dist-info/namespace_packages.txt
flytekitplugins_data_fsspec-1.16.12.dist-info/top_level.txt
flytekitplugins_data_fsspec-1.16.12.dist-info/RECORD
